summarizium/__init__.py
summarizium/main.py
summarizium-0.0.0.dist-info/LICENSE
summarizium-0.0.0.dist-info/METADATA
summarizium-0.0.0.dist-info/WHEEL
summarizium-0.0.0.dist-info/top_level.txt
summarizium-0.0.0.dist-info/RECORD
