Metadata-Version: 2.1
Name: summarizium
Version: 0.0.0
Author: Sébastien De Revière
Classifier: Programming Language :: Python :: 3
Classifier: License :: OSI Approved :: Apache Software License
Classifier: Operating System :: OS Independent
Requires-Python: >=3.8
License-File: LICENSE
Provides-Extra: ci
Requires-Dist: pytest ; extra == 'ci'
Requires-Dist: ruff ; extra == 'ci'
Provides-Extra: lint_and_format
Requires-Dist: ruff ; extra == 'lint_and_format'
Provides-Extra: pypi
Requires-Dist: twine ; extra == 'pypi'
Requires-Dist: wheel ; extra == 'pypi'
Provides-Extra: test
Requires-Dist: pytest ; extra == 'test'
